LICENSE
MANIFEST.in
README.md
pyproject.toml
requirements.txt
setup.cfg
setup.py
bash_workbench/__init__.py
bash_workbench/args.py
bash_workbench/asset.py
bash_workbench/dataset.py
bash_workbench/datasets.py
bash_workbench/filelib.py
bash_workbench/folder_hierarchy.py
bash_workbench/launch.py
bash_workbench/logging.py
bash_workbench/menu.py
bash_workbench/misc.py
bash_workbench/params_menu.py
bash_workbench/repository.py
bash_workbench/timestamp.py
bash_workbench/workbench.py
bash_workbench/workbench_config.py
bash_workbench.egg-info/PKG-INFO
bash_workbench.egg-info/SOURCES.txt
bash_workbench.egg-info/dependency_links.txt
bash_workbench.egg-info/entry_points.txt
bash_workbench.egg-info/requires.txt
bash_workbench.egg-info/top_level.txt
bash_workbench/helpers/run_launcher
bash_workbench/helpers/run_tool
bash_workbench/helpers/set_dataset_attribute