Metadata-Version: 2.1
Name: bash-workbench
Version: 0.0.14
Summary: Dataset manager for more reproducible analysis with shell scripts
Home-page: https://github.com/FredHutch/bash-workbench
Author: Samuel Minot
Author-email: sminot@fredhutch.org
License: MIT
Platform: UNKNOWN
License-File: LICENSE
